setup.cfg
setup.py
SQLAlchemyAggregator.egg-info/PKG-INFO
SQLAlchemyAggregator.egg-info/SOURCES.txt
SQLAlchemyAggregator.egg-info/dependency_links.txt
SQLAlchemyAggregator.egg-info/requires.txt
SQLAlchemyAggregator.egg-info/top_level.txt
aggregator/__init__.py
tests/simpletest.py
