Metadata-Version: 1.0
Name: SQLAlchemyAggregator
Version: 0.1.3.dev-r805
Summary: SQLAlchemy's mapper extension which canautomatically track changes in mapped classes andcalculate aggregations based on them
Home-page: http://www.mr-pc.kiev.ua/en/projects/SQLAlchemyAggregator
Author: Paul Colomiets
Author-email: pc@gafol.net
License: MIT
Keywords: sql sqlalchemy aggragation database
Platform: UNKNOWN
